ramp_database/__init__.py
ramp_database/_version.py
ramp_database/cli.py
ramp_database/exceptions.py
ramp_database/testing.py
ramp_database/utils.py
ramp_database/model/__init__.py
ramp_database/model/base.py
ramp_database/model/datatype.py
ramp_database/model/event.py
ramp_database/model/fold.py
ramp_database/model/problem.py
ramp_database/model/score.py
ramp_database/model/submission.py
ramp_database/model/team.py
ramp_database/model/user.py
ramp_database/model/workflow.py
ramp_database/model/tests/__init__.py
ramp_database/model/tests/test_event.py
ramp_database/model/tests/test_fold.py
ramp_database/model/tests/test_problem.py
ramp_database/model/tests/test_score.py
ramp_database/model/tests/test_submission.py
ramp_database/model/tests/test_team.py
ramp_database/model/tests/test_user.py
ramp_database/model/tests/test_workflow.py
ramp_database/tests/__init__.py
ramp_database/tests/test_cli.py
ramp_database/tests/test_exceptions.py
ramp_database/tests/test_testing.py
ramp_database/tests/test_utils.py
ramp_database/tests/data/__init__.py
ramp_database/tests/data/ramp_config_boston_housing.yml
ramp_database/tests/data/ramp_config_iris.yml
ramp_database/tools/__init__.py
ramp_database/tools/_query.py
ramp_database/tools/contributivity.py
ramp_database/tools/database.py
ramp_database/tools/event.py
ramp_database/tools/frontend.py
ramp_database/tools/leaderboard.py
ramp_database/tools/submission.py
ramp_database/tools/team.py
ramp_database/tools/user.py
ramp_database/tools/tests/__init__.py
ramp_database/tools/tests/test_database.py
ramp_database/tools/tests/test_event.py
ramp_database/tools/tests/test_frontend.py
ramp_database/tools/tests/test_leaderboard.py
ramp_database/tools/tests/test_query.py
ramp_database/tools/tests/test_submission.py
ramp_database/tools/tests/test_team.py
ramp_database/tools/tests/test_user.py
ramp_database-0.10.1.dist-info/LICENSE
ramp_database-0.10.1.dist-info/METADATA
ramp_database-0.10.1.dist-info/WHEEL
ramp_database-0.10.1.dist-info/entry_points.txt
ramp_database-0.10.1.dist-info/top_level.txt
ramp_database-0.10.1.dist-info/RECORD
